pyntacle/__init__.py
pyntacle/config.py
pyntacle/pyntacle.py
pyntacle/algorithms/__init__.py
pyntacle/algorithms/bruteforce_search.py
pyntacle/algorithms/global_topology.py
pyntacle/algorithms/greedy_optimization.py
pyntacle/algorithms/keyplayer.py
pyntacle/algorithms/local_topology.py
pyntacle/algorithms/scalefree_inference.py
pyntacle/algorithms/shortest_path.py
pyntacle/algorithms/shortest_path_gpu.py
pyntacle/algorithms/sparseness.py
pyntacle/algorithms/stochastic_gradient_descent.py
pyntacle/cmds/__init__.py
pyntacle/cmds/communities.py
pyntacle/cmds/convert.py
pyntacle/cmds/generate.py
pyntacle/cmds/group_centrality.py
pyntacle/cmds/keyplayer.py
pyntacle/cmds/metrics.py
pyntacle/cmds/set.py
pyntacle/cmds/cmds_utils/__init__.py
pyntacle/cmds/cmds_utils/group_search_wrapper.py
pyntacle/cmds/cmds_utils/pyntacleink_template.py
pyntacle/cmds/cmds_utils/reporter.py
pyntacle/exceptions/__init__.py
pyntacle/exceptions/generic_error.py
pyntacle/exceptions/illegal_graph_size_error.py
pyntacle/exceptions/illegal_kpset_size_error.py
pyntacle/exceptions/improperly_formatted_file_error.py
pyntacle/exceptions/multiple_solutions_error.py
pyntacle/exceptions/unsupported_graph_error.py
pyntacle/exceptions/wrong_argument_error.py
pyntacle/graph_operations/__init__.py
pyntacle/graph_operations/communities.py
pyntacle/graph_operations/set_operations.py
pyntacle/internal/__init__.py
pyntacle/internal/binarycheck.py
pyntacle/internal/graph_load.py
pyntacle/internal/group_search_utils.py
pyntacle/internal/io_utils.py
pyntacle/internal/name_checker.py
pyntacle/internal/timeit.py
pyntacle/io_stream/__init__.py
pyntacle/io_stream/converter.py
pyntacle/io_stream/export_attributes.py
pyntacle/io_stream/exporter.py
pyntacle/io_stream/generator.py
pyntacle/io_stream/import_attributes.py
pyntacle/io_stream/importer.py
pyntacle/pyntacletests/__init__.py
pyntacle/pyntacletests/test_suite.py
pyntacle/pyntacletests/test_widgets_communities.py
pyntacle/pyntacletests/test_widgets_convert.py
pyntacle-1.3.2.dist-info/LICENSE
pyntacle-1.3.2.dist-info/METADATA
pyntacle-1.3.2.dist-info/WHEEL
pyntacle-1.3.2.dist-info/entry_points.txt
pyntacle-1.3.2.dist-info/top_level.txt
pyntacle-1.3.2.dist-info/RECORD
