Metadata-Version: 2.1
Name: pyntacle
Version: 1.3.2
Summary: A Python package for network analysis based on non-canonical metrics and HPC-Computing
Home-page: http://pyntacle.css-mendel.it
Author: Tommaso Mazza
Author-email: bioinformatics@css-mendel.it
License: GPL3
Project-URL: Documentation, http://pyntacle.css-mendel.it:10080/#docs
Project-URL: Source, https://github.com/mazzalab/pyntacle
Project-URL: Tracker, https://github.com/mazzalab/pyntacle/issues
Project-URL: Developmental plan, https://github.com/mazzalab/pyntacle/projects
Keywords: network,graph,systems biology,bioinformatics
Platform: UNKNOWN
Classifier: Development Status :: 5 - Production/Stable
Classifier: Intended Audience :: Science/Research
Classifier: Programming Language :: Python :: 3.7
Classifier: License :: OSI Approved :: GNU General Public License v3 (GPLv3)
Classifier: Operating System :: OS Independent
Requires-Python: >=3.7,<3.8
Requires-Dist: pandas (==1.1.4)
Requires-Dist: seaborn (==0.11.0)
Requires-Dist: setuptools
Requires-Dist: colorama (==0.4.4)
Requires-Dist: numba (==0.51.2)
Requires-Dist: ordered-set (==4.0.2)
Requires-Dist: python-igraph (==0.8.3)
Requires-Dist: xlsxwriter (==1.3.7)
Requires-Dist: psutil
